{
  "timestamp": "07/21/2026 12:50 PM",
  "regiones": {
    "ARECIBO": {
      "averia": 930,
      "planificados": 176,
      "total": 1106
    },
    "BAYAMON": {
      "averia": 391,
      "planificados": 640,
      "total": 1031
    },
    "CAROLINA": {
      "averia": 227,
      "planificados": 0,
      "total": 227
    },
    "CAGUAS": {
      "averia": 2624,
      "planificados": 6265,
      "total": 8889
    },
    "MAYAGUEZ": {
      "averia": 3544,
      "planificados": 51,
      "total": 3595
    },
    "PONCE": {
      "averia": 223,
      "planificados": 2013,
      "total": 2236
    },
    "SAN JUAN": {
      "averia": 3962,
      "planificados": 0,
      "total": 3962
    }
  }
}