{
  "timestamp": "07/23/2026 11:00 AM",
  "regiones": {
    "ARECIBO": {
      "averia": 190,
      "planificados": 212,
      "total": 402
    },
    "BAYAMON": {
      "averia": 475,
      "planificados": 1122,
      "total": 1597
    },
    "CAROLINA": {
      "averia": 3614,
      "planificados": 0,
      "total": 3614
    },
    "CAGUAS": {
      "averia": 1503,
      "planificados": 56,
      "total": 1559
    },
    "MAYAGUEZ": {
      "averia": 76,
      "planificados": 0,
      "total": 76
    },
    "PONCE": {
      "averia": 8931,
      "planificados": 2476,
      "total": 11407
    },
    "SAN JUAN": {
      "averia": 122,
      "planificados": 173,
      "total": 295
    }
  }
}